shellshock/__init__.py
shellshock/convert.py
shellshock/main.py
shellshock/executors/__init__.py
shellshock/executors/shell.py
shellshock/helpers/__init__.py
shellshock/helpers/shell.py
shellshock/parse/__init__.py
shellshock/parse/_template.py
shellshock/parse/body.py
shellshock/parse/controlflow/__init__.py
shellshock/parse/controlflow/_break.py
shellshock/parse/controlflow/_continue.py
shellshock/parse/controlflow/_for.py
shellshock/parse/controlflow/_if.py
shellshock/parse/controlflow/_try.py
shellshock/parse/controlflow/_while.py
shellshock/parse/controlflow/_with.py
shellshock/parse/controlflow/excepthandler.py
shellshock/parse/controlflow/tryexcept.py
shellshock/parse/controlflow/tryfinally.py
shellshock/parse/controlflow/withitem.py
shellshock/parse/expressions/__init__.py
shellshock/parse/expressions/_and.py
shellshock/parse/expressions/_in.py
shellshock/parse/expressions/_is.py
shellshock/parse/expressions/_not.py
shellshock/parse/expressions/_or.py
shellshock/parse/expressions/add.py
shellshock/parse/expressions/attribute.py
shellshock/parse/expressions/binop.py
shellshock/parse/expressions/bitand.py
shellshock/parse/expressions/bitor.py
shellshock/parse/expressions/bitxor.py
shellshock/parse/expressions/boolop.py
shellshock/parse/expressions/call.py
shellshock/parse/expressions/compare.py
shellshock/parse/expressions/comprehension.py
shellshock/parse/expressions/dictcomp.py
shellshock/parse/expressions/div.py
shellshock/parse/expressions/eq.py
shellshock/parse/expressions/expr.py
shellshock/parse/expressions/extslice.py
shellshock/parse/expressions/floordiv.py
shellshock/parse/expressions/generatorexp.py
shellshock/parse/expressions/gt.py
shellshock/parse/expressions/gte.py
shellshock/parse/expressions/ifexp.py
shellshock/parse/expressions/index.py
shellshock/parse/expressions/invert.py
shellshock/parse/expressions/isnot.py
shellshock/parse/expressions/keyword.py
shellshock/parse/expressions/listcomp.py
shellshock/parse/expressions/lshift.py
shellshock-0.0.1.dist-info/METADATA
shellshock-0.0.1.dist-info/WHEEL
shellshock-0.0.1.dist-info/entry_points.txt
shellshock-0.0.1.dist-info/top_level.txt
shellshock-0.0.1.dist-info/RECORD
