Metadata-Version: 2.1
Name: shellshock
Version: 0.0.1
Summary: Write your shell scripts using Python
Home-page: https://github.com/mattdodge/shellshock
Author: Matt Dodge
Author-email: mattedgod@gmail.com
License: UNKNOWN
Platform: UNKNOWN
